PyQt5/Qsci.abi3.so
PyQt5/Qsci.pyi
PyQt5/Qt5/qsci/api/python/Python-2.4.api
PyQt5/Qt5/qsci/api/python/Python-2.5.api
PyQt5/Qt5/qsci/api/python/Python-2.6.api
PyQt5/Qt5/qsci/api/python/Python-2.7.api
PyQt5/Qt5/qsci/api/python/Python-3.1.api
PyQt5/Qt5/qsci/api/python/Python-3.10.api
PyQt5/Qt5/qsci/api/python/Python-3.11.api
PyQt5/Qt5/qsci/api/python/Python-3.2.api
PyQt5/Qt5/qsci/api/python/Python-3.3.api
PyQt5/Qt5/qsci/api/python/Python-3.4.api
PyQt5/Qt5/qsci/api/python/Python-3.5.api
PyQt5/Qt5/qsci/api/python/Python-3.6.api
PyQt5/Qt5/qsci/api/python/Python-3.7.api
PyQt5/Qt5/qsci/api/python/Python-3.8.api
PyQt5/Qt5/qsci/api/python/Python-3.9.api
PyQt5/Qt5/qsci/api/python/QScintilla.api
PyQt5/Qt5/translations/qscintilla_cs.qm
PyQt5/Qt5/translations/qscintilla_de.qm
PyQt5/Qt5/translations/qscintilla_es.qm
PyQt5/Qt5/translations/qscintilla_fr.qm
PyQt5/Qt5/translations/qscintilla_pt_br.qm
PyQt5/bindings/Qsci/Qsci.toml
PyQt5/bindings/Qsci/qsciabstractapis.sip
PyQt5/bindings/Qsci/qsciapis.sip
PyQt5/bindings/Qsci/qscicommand.sip
PyQt5/bindings/Qsci/qscicommandset.sip
PyQt5/bindings/Qsci/qscidocument.sip
PyQt5/bindings/Qsci/qscilexer.sip
PyQt5/bindings/Qsci/qscilexerasm.sip
PyQt5/bindings/Qsci/qscilexeravs.sip
PyQt5/bindings/Qsci/qscilexerbash.sip
PyQt5/bindings/Qsci/qscilexerbatch.sip
PyQt5/bindings/Qsci/qscilexercmake.sip
PyQt5/bindings/Qsci/qscilexercoffeescript.sip
PyQt5/bindings/Qsci/qscilexercpp.sip
PyQt5/bindings/Qsci/qscilexercsharp.sip
PyQt5/bindings/Qsci/qscilexercss.sip
PyQt5/bindings/Qsci/qscilexercustom.sip
PyQt5/bindings/Qsci/qscilexerd.sip
PyQt5/bindings/Qsci/qscilexerdiff.sip
PyQt5/bindings/Qsci/qscilexerfortran.sip
PyQt5/bindings/Qsci/qscilexerfortran77.sip
PyQt5/bindings/Qsci/qscilexerhex.sip
PyQt5/bindings/Qsci/qscilexerhtml.sip
PyQt5/bindings/Qsci/qscilexeridl.sip
PyQt5/bindings/Qsci/qscilexerintelhex.sip
PyQt5/bindings/Qsci/qscilexerjava.sip
PyQt5/bindings/Qsci/qscilexerjavascript.sip
PyQt5/bindings/Qsci/qscilexerjson.sip
QScintilla-2.14.1.dist-info/WHEEL
QScintilla-2.14.1.dist-info/METADATA
QScintilla-2.14.1.dist-info/RECORD
