Metadata-Version: 2.1
Name: QScintilla
Version: 2.14.1
Requires-Python: >=3.7
Summary: Python bindings for the QScintilla programmers editor widget
Home-Page: https://www.riverbankcomputing.com/software/qscintilla/
Author: Riverbank Computing Limited
Author-Email: info@riverbankcomputing.com
License: GPL v3
Requires-Dist: PyQt5 (>=5.15.4)
